incus_sdk/__init__.py
incus_sdk/client.py
incus_sdk/exceptions.py
incus_sdk/utils.py
incus_sdk/api/__init__.py
incus_sdk/api/certificates.py
incus_sdk/api/client.py
incus_sdk/api/cluster.py
incus_sdk/api/images.py
incus_sdk/api/instances.py
incus_sdk/api/networks.py
incus_sdk/api/operations.py
incus_sdk/api/profiles.py
incus_sdk/api/projects.py
incus_sdk/api/storage_pools.py
incus_sdk/models/__init__.py
incus_sdk/models/base.py
incus_sdk/models/certificate.py
incus_sdk/models/cluster.py
incus_sdk/models/image.py
incus_sdk/models/instance.py
incus_sdk/models/network.py
incus_sdk/models/profile.py
incus_sdk/models/project.py
incus_sdk/models/storage_pool.py
incus_sdk-1.0.0.dist-info/METADATA
incus_sdk-1.0.0.dist-info/WHEEL
incus_sdk-1.0.0.dist-info/top_level.txt
incus_sdk-1.0.0.dist-info/RECORD
