Metadata-Version: 2.4
Name: incus_sdk
Version: 1.0.0
Summary: A Python SDK for the Incus API
Home-page: https://github.com/orbical-dev/incus_sdk
Author: Incus SDK Team
Author-email: zacharyj@orbical.dev
Classifier: Development Status :: 3 - Alpha
Classifier: Intended Audience :: Developers
Classifier: License :: OSI Approved :: MIT License
Classifier: Programming Language :: Python :: 3
Classifier: Programming Language :: Python :: 3.7
Classifier: Programming Language :: Python :: 3.8
Classifier: Programming Language :: Python :: 3.9
Classifier: Programming Language :: Python :: 3.10
Classifier: Programming Language :: Python :: 3.11
Requires-Python: >=3.7
Requires-Dist: aiohttp>=3.8.0
Requires-Dist: certifi>=2021.10.8
Requires-Dist: aiofiles>=0.8.0
Dynamic: author
Dynamic: author-email
Dynamic: classifier
Dynamic: description
Dynamic: description-content-type
Dynamic: home-page
Dynamic: requires-dist
Dynamic: requires-python
Dynamic: summary
